[
  {
    "title": "10× Algorithm Updated",
    "message": "අපගේ SHA512-based Aviator signal යෙදුමේ (10x) පුරෝකථනය සඳහා ඇල්ගොරිතමය යාවත්කාලීන කර ඇත. මෙම යාවත්කාලීනතාවය 10× අවස්ථාවල නිවැරදිභාවය හා අනාවැකි සංවේදනය වැඩිදියුණු කරයි.",
    "type": "algorithm_update",
    "timestamp": "2025-08-10T14:00:00Z"
  },
  {
    "title": "Bug Fixed",
    "message": "Countdown Timer ක්‍රියාවලියේ සිදුවූ දෝෂයක් නිවැරදි කරන ලදි.",
    "type": "bug_fix",
    "timestamp": "2025-07-18T14:15:00Z"
  },
  {
    "title": "Welcome Message",
    "message": "නව තොරතුරැ සහ උපදෙස් සඳහා Telegram channel එක සමඟ සම්බන්ධ වන්න.",
    "type": "general",
    "timestamp": "2025-08-14T07:00:00Z"
  },
  {
    "title": "10× Signal — Play at the correct time / 10× සිග්නල් — නිවැරදි කාලයට ක්‍රීඩා කරන්න",
    "message": "උදාහරණය :- Sha512 Hash ඇතුළත් කිරීමෙන්\n\nලැබුණු 10x සංඥා කාලය\n\n10:23:33 නම්, එහි තත්පර ඉවත් කර 10:23 ලෙස වේලාව සකස්කරන්න. විනාඩි 2ක කාලයක් සඳහා (10:23 මත) ක්‍රීඩා කරන්න. සම්බන්ධිත Signal කාල පරාසය: 10:22:45 සිට 10:25:15 දක්වා (±15s).\n\nඋදාහරණය:\n10:23:33 → 10:23\n10:23 → 10:22:45 // 10:25:15\n\nමෙම කාලය අතරතුර bet කරන්න.",
    "message_si": "උදාහරණය :- Sha512 Hash ඇතුළත් කිරීමෙන්\n\nලැබුණු 10x සංඥා කාලය\n\n10:23:33 නම්, එහි තත්පර ඉවත් කර 10:23 ලෙස වේලාව සකස්කරන්න. විනාඩි 2ක කාලයක් සඳහා (10:23 මත) ක්‍රීඩා කරන්න. සම්බන්ධිත Signal කාල පරාසය: 10:22:45 සිට 10:25:15 දක්වා (±15s).\n\nඋදාහරණය:\n10:23:33 → 10:23\n10:23 → 10:22:45 // 10:25:15\n\nමෙම කාලය අතරතුර bet කරන්න.",
    "type": "high_risk_signal",
    "timestamp": "2025-08-27T06:00:00Z"
  }
]